<?xml version='1.0' encoding='utf-8'?>
<workflows version="1.0" generated="2025-09-03T04:36:30"><workflow id="W01" scene="S01" presetU61="U61-P01" presetU62="U62-P01" playable="true" hands="2"><description>Jam Full: J-6 spielt S-1/TL; Clock an alle. Stereo-Summe über L-6.</description></workflow><workflow id="W02" scene="S02" presetU61="U61-P02" presetU62="U62-P02" playable="true" hands="1"><description>Vocal Focus: E-4 im Vordergrund; TL Solo, T-8 nur Clock.</description></workflow><workflow id="W03" scene="S03" presetU61="U61-P03" presetU62="U62-P03" playable="true" hands="2"><description>TL Play: J-6 → TL Noten; Drum Solo via T-8; TL Freeze über CC31 möglich.</description></workflow></workflows>